mc_plugin_strcreator/__init__.py
mc_plugin_strcreator/cli.py
mc_plugin_strcreator/generator.py
mc_plugin_strcreator-0.1.3.dist-info/licenses/LICENSE
mc_plugin_strcreator-0.1.3.dist-info/METADATA
mc_plugin_strcreator-0.1.3.dist-info/WHEEL
mc_plugin_strcreator-0.1.3.dist-info/entry_points.txt
mc_plugin_strcreator-0.1.3.dist-info/top_level.txt
mc_plugin_strcreator-0.1.3.dist-info/RECORD
