Metadata-Version: 2.4
Name: mc-plugin-strcreator
Version: 0.1.3
Summary: A CLI tool to scaffold a basic Minecraft plugin folder structure
Home-page: https://github.com/NotGamerPratham/mcplstrcreator
Author: NotGamerPratham
Author-email: NotGamerPratham <contact@notgamerpratham.com>
License: MIT License
Classifier: Programming Language :: Python :: 3
Classifier: License :: OSI Approved :: MIT License
Classifier: Operating System :: OS Independent
Requires-Python: >=3.6
License-File: LICENSE
Dynamic: author
Dynamic: home-page
Dynamic: license-file
Dynamic: requires-python
